{
    "order": 1,
    "title": {
        "en": "Scheherazade",
        "id": "Scheherazade"
    },
    "fonts" : {
        "google": ["Scheherazade:400:arabic", "Lato:400,400i,700"]
    },
    "size" : {
        "w": 1024,
        "h": 1024
    },
    "designProperties": {
        "background": {
            "label": {
                "en" : "Background Upload",
                "id" : "Upload Latar Belakang"
            },
            "input": "image",
            "value": "__designDataUrl__/design-assets/images/reed-546250.jpg"
        },
        "backgroundBlur": {
            "label": {
                "en" : "Background Bokeh",
                "id" : "Blur Latar Belakang"
            },
            "input": "range",
            "value": 5,
            "min": 0,
            "max": 50
        },
        "backgroundDarken": {
            "label" : {
                "en" : "Background Darkness",
                "id" : "Pergelap latar"
            },
            "input": "range",
            "value": "0.4",
            "min": 0,
            "max": 1,
            "step": ".01"
        },
        "textWidth": {
            "label" : {
                "en" : "Text Width",
                "id" : "Lebar Teks"
            },
            "input": "range",
            "value": 800,
            "min": 300,
            "max": 1000
        },
        "sep1": {
            "input": "separator"
        },
        "title" : {
            "label": {
                "en" : "Title",
                "id" : "Judul"
            },
            "input": "text",
            "value": "Someone for whom a favour is done and he repays"
        },
        "titleFontSize": {
            "label": {
                "en" : "Title Font Size",
                "id" : "Ukuran Font Judul"
            },
            "input": "range",
            "value": 46,
            "min": 10,
            "max": 100
        },
        "sep2": {
            "input": "separator"
        },
        "subtitle" : {
            "label": {
                "en" : "Subtitle",
                "id" : "Subjudul"
            },
            "input": "text",
            "value": "Jabir ibn 'Abdullah al-Ansari reported that the Prophet (ﷺ), said,"
        },
        "subtitleFontSize": {
            "label": {
                "en" : "Subtitle Font Size",
                "id" : "Ukuran Font Subjudul"
            },
            "input": "range",
            "value": 28,
            "min": 10,
            "max": 100
        },
        "sep3": {
            "input": "separator"
        },
        "maintext" : {
            "label": {
                "en" : "Main Text",
                "id" : "Teks Utama"
            },
            "input": "text",
            "value": "مَنْ صُنِعَ إِلَيْهِ مَعْرُوفٌ فَلْيُجْزِئْهُ، فَإِنْ لَمْ يَجِدْ مَا يُجْزِئُهُ فَلْيُثْنِ عَلَيْهِ، فَإِنَّهُ إِذَا أَثْنَى فَقَدْ شَكَرَهُ، وَإِنْ كَتَمَهُ فَقَدْ كَفَرَهُ، وَمَنْ تَحَلَّى بِمَا لَمْ يُعْطَ، فَكَأَنَّمَا لَبِسَ ثَوْبَيْ زُورٍ"
        },
        "maintextFontSize": {
            "label": {
                "en" : "Main Text Font Size",
                "id" : "Ukuran Font Teks Utama"
            },
            "input": "range",
            "value": 52,
            "min": 10,
            "max": 100
        },
        "sep4": {
            "input": "separator"
        },
        "description" : {
            "label": {
                "en" : "Description",
                "id" : "Deskripsi"
            },
            "input": "text",
            "value": "Whoever has a favour done for him should repay it. If he cannot find anything he can use to repay it, he should praise the one who did it. When he praises him, he thanks him. If he is silent, he is ungrateful to him. If someone adorns himself with something he has not been given, it is as if he was wearing a false garment."
        },
        "descriptionFontSize": {
            "label": {
                "en" : "Description Font Size",
                "id" : "Ukuran Font Deskripsi"
            },
            "input": "range",
            "value": 28,
            "min": 10,
            "max": 100
        },
        "sep5": {
            "input": "separator"
        },
        "notes" : {
            "label": {
                "en" : "Notes",
                "id" : "Catatan"
            },
            "input": "text",
            "value": "Al-Adab Al-Mufrad, Book 10, Hadith 215.<br>Grade: Sahih (Al-Albani)"
        },
        "notesFontSize": {
            "label": {
                "en" : "Notes Font Size",
                "id" : "Ukuran Font Catatan"
            },
            "input": "range",
            "value": 26,
            "min": 10,
            "max": 100
        }
    }
}